test/empo.py
rtyuzer-0.3.0.dist-info/METADATA
rtyuzer-0.3.0.dist-info/WHEEL
rtyuzer-0.3.0.dist-info/top_level.txt
rtyuzer-0.3.0.dist-info/RECORD
