Metadata-Version: 2.4
Name: rtyuzer
Version: 0.3.0
Summary: Add your description here
Requires-Python: >=3.13
Requires-Dist: click>=8.3.0
Requires-Dist: fastapi>=0.116.2
Requires-Dist: greenlet>=3.2.4
Requires-Dist: httpx>=0.28.1
Requires-Dist: lupa>=2.5
Requires-Dist: nanoid>=2.0.0
Requires-Dist: numba>=0.62.0
Requires-Dist: ollama>=0.5.4
Requires-Dist: passlib[bcrypt]>=1.7.4
Requires-Dist: psycopg[c]>=3.2.10
Requires-Dist: python-jose>=3.5.0
Requires-Dist: regex>=2025.9.18
Requires-Dist: rich>=14.1.0
Requires-Dist: rply>=0.7.8
Requires-Dist: scikit-learn>=1.7.2
Requires-Dist: scipy>=1.16.2
Requires-Dist: uvicorn>=0.35.0
